executor_s3/__init__.py
executor_s3/_config.py
executor_s3/_impl.py
executor_s3/hash-tar.sh
executor_s3-0.0.12.dist-info/METADATA
executor_s3-0.0.12.dist-info/WHEEL
executor_s3-0.0.12.dist-info/top_level.txt
executor_s3-0.0.12.dist-info/RECORD
